odoo/addons/project_stakeholder/README.rst
odoo/addons/project_stakeholder/__init__.py
odoo/addons/project_stakeholder/__manifest__.py
odoo/addons/project_stakeholder/i18n/it.po
odoo/addons/project_stakeholder/i18n/project_stakeholder.pot
odoo/addons/project_stakeholder/models/__init__.py
odoo/addons/project_stakeholder/models/project_project.py
odoo/addons/project_stakeholder/models/project_stakeholder.py
odoo/addons/project_stakeholder/models/project_stakeholder_role.py
odoo/addons/project_stakeholder/models/res_partner.py
odoo/addons/project_stakeholder/readme/CONTRIBUTORS.md
odoo/addons/project_stakeholder/readme/DESCRIPTION.md
odoo/addons/project_stakeholder/security/ir.model.access.csv
odoo/addons/project_stakeholder/static/description/icon.png
odoo/addons/project_stakeholder/static/description/index.html
odoo/addons/project_stakeholder/tests/__init__.py
odoo/addons/project_stakeholder/tests/test_project_stakeholder.py
odoo/addons/project_stakeholder/views/project_project.xml
odoo/addons/project_stakeholder/views/project_stakeholder_role.xml
odoo/addons/project_stakeholder/views/res_partner.xml
odoo_addon_project_stakeholder-18.0.1.0.0.4.dist-info/METADATA
odoo_addon_project_stakeholder-18.0.1.0.0.4.dist-info/WHEEL
odoo_addon_project_stakeholder-18.0.1.0.0.4.dist-info/top_level.txt
odoo_addon_project_stakeholder-18.0.1.0.0.4.dist-info/RECORD
